{
  "handlers": {
    "echo": "../custom-handler/echo-handler.mjs",
    "simple": {
      "specPaths": ["../openapi/simple.yaml"],
      "baseUrl": "https://api.example.com",
      "operationFilter": { "method": "get" },
      "handler": "../custom-handler/openapi-override.mjs"
    }
  },
  "flowsDir": "../flows",
  "params": [
    { "name": "env", "type": "string", "default": "example" },
    { "name": "name", "type": "string", "default": "Guest" },
    { "name": "count", "type": "number", "default": 1 }
  ]
}
